Metadata-Version: 1.1
Name: deoxys-image
Version: 0.0.3
Summary: Image transformation
Home-page: https://github.com/huynhngoc/deoxys-image
Author: Ngoc Huynh Bao
Author-email: ngoc.huynh.bao@nmbu.no
License: "MIT license",
Keywords: deoxys-image
Platform: UNKNOWN
Classifier: Intended Audience :: Developers
Classifier: License :: OSI Approved :: MIT License
Classifier: Natural Language :: English
Classifier: Programming Language :: Python :: 3.6
Classifier: Programming Language :: Python :: 3.7
